django_workflow_system/__init__.py
django_workflow_system/apps.py
django_workflow_system/views.py
django_workflow_system/admin/__init__.py
django_workflow_system/admin/collection.py
django_workflow_system/admin/collection_dependency.py
django_workflow_system/admin/everything_else.py
django_workflow_system/admin/step.py
django_workflow_system/api/__init__.py
django_workflow_system/api/serializers/__init__.py
django_workflow_system/api/serializers/user/__init__.py
django_workflow_system/api/serializers/user/workflows/__init__.py
django_workflow_system/api/serializers/user/workflows/assignment.py
django_workflow_system/api/serializers/user/workflows/engagement.py
django_workflow_system/api/serializers/user/workflows/engagement_detail.py
django_workflow_system/api/serializers/user/workflows/recommendation.py
django_workflow_system/api/serializers/user/workflows/subscription.py
django_workflow_system/api/serializers/utils/__init__.py
django_workflow_system/api/serializers/utils/get_images_helper.py
django_workflow_system/api/serializers/workflows/__init__.py
django_workflow_system/api/serializers/workflows/author.py
django_workflow_system/api/serializers/workflows/collection.py
django_workflow_system/api/serializers/workflows/step.py
django_workflow_system/api/serializers/workflows/workflow.py
django_workflow_system/api/tests/__init__.py
django_workflow_system/api/tests/utils.py
django_workflow_system/api/tests/factories/__init__.py
django_workflow_system/api/tests/factories/user.py
django_workflow_system/api/tests/factories/workflows/__init__.py
django_workflow_system/api/tests/factories/workflows/assignment.py
django_workflow_system/api/tests/factories/workflows/authors.py
django_workflow_system/api/tests/factories/workflows/engagement.py
django_workflow_system/api/tests/factories/workflows/json_schema.py
django_workflow_system/api/tests/factories/workflows/metadata.py
django_workflow_system/api/tests/factories/workflows/recommendation.py
django_workflow_system-0.9.13.dist-info/LICENSE
django_workflow_system-0.9.13.dist-info/METADATA
django_workflow_system-0.9.13.dist-info/WHEEL
django_workflow_system-0.9.13.dist-info/top_level.txt
django_workflow_system-0.9.13.dist-info/RECORD
