Metadata-Version: 2.1
Name: django-workflow-system
Version: 0.9.13
Summary: A highly customizable workflow system for Django. Create surveys, activities, etc.
Home-page: UNKNOWN
Author: Center for Research Computing
Author-email: prometheus-team@nd.edu
License: MIT
Platform: UNKNOWN
Classifier: Environment :: Web Environment
Classifier: Framework :: Django
Classifier: Framework :: Django :: 3.1
Classifier: Intended Audience :: Developers
Classifier: License :: OSI Approved :: MIT License
Classifier: Operating System :: OS Independent
Classifier: Programming Language :: Python
Classifier: Programming Language :: Python :: 3
Classifier: Programming Language :: Python :: 3 :: Only
Classifier: Programming Language :: Python :: 3.8
Classifier: Topic :: Internet :: WWW/HTTP
Classifier: Topic :: Internet :: WWW/HTTP :: Dynamic Content
Requires-Python: >3.8
License-File: LICENSE
Requires-Dist: Pillow (>=6.2.0)
Requires-Dist: jsonschema (>=3.0.1)
Requires-Dist: Django (>=3.1.0)
Requires-Dist: djangorestframework (>=3.12.2)
Requires-Dist: factory-boy (>=3.2.0)
